openregister/__init__.py
openregister/__main__.py
openregister/cli.py
openregister/client.py
openregister/config.py
openregister/entry.py
openregister/item.py
openregister/record.py
openregister/representation.py
openregister/server.py
openregister/store.py
openregister/views.py
openregister/writer.py
openregister/datatypes/__init__.py
openregister/datatypes/digest.py
openregister/representations/__init__.py
openregister/representations/csv.py
openregister/representations/json.py
openregister/representations/jsonl.py
openregister/representations/tsv.py
openregister/representations/txt.py
openregister/representations/yaml.py
openregister/stores/__init__.py
openregister/stores/file.py
openregister/stores/memory.py
tests/__init__.py
tests/test_client.py
tests/test_entry.py
tests/test_hash.py
tests/test_item.py
tests/test_reader_json.py
tests/test_reader_jsonl.py
tests/test_reader_tsv.py
tests/test_record.py
tests/test_representation_csv.py
tests/test_representation_json.py
tests/test_representation_jsonl.py
tests/test_representation_tsv.py
tests/test_representation_txt.py
tests/test_representation_yaml.py
tests/test_set.py
tests/test_store.py
tests/test_store_file.py
tests/test_store_memory.py
tests/test_writer.py
tests/test_writer_csv.py
tests/test_writer_json.py
tests/test_writer_jsonl.py
tests/test_writer_tsv.py
tests/test_writer_txt.py
tests/test_writer_yaml.py
openregister-0.8.9.dist-info/LICENSE
openregister-0.8.9.dist-info/METADATA
openregister-0.8.9.dist-info/WHEEL
openregister-0.8.9.dist-info/entry_points.txt
openregister-0.8.9.dist-info/top_level.txt
openregister-0.8.9.dist-info/RECORD
