Metadata-Version: 2.1
Name: openregister
Version: 0.8.9
Summary: Publishing tools for GOV.UK style registers
Home-page: https://github.com/psd/openregister
Author: Paul Downey
Author-email: paul.downey@whatfettle.com
License: MIT
Platform: UNKNOWN
Classifier: Development Status :: 3 - Alpha
Classifier: Intended Audience :: Developers
Classifier: Topic :: Database
Classifier: License :: OSI Approved :: MIT License
Classifier: Programming Language :: Python :: 3.5
Classifier: Programming Language :: Python :: 3.6
Classifier: Programming Language :: Python :: 3.7
Requires-Dist: click (==7.0)
Requires-Dist: click-default-group (==1.2)
Requires-Dist: PyYAML (==3.13)
Requires-Dist: requests (==2.22.0)
Requires-Dist: Sanic (==0.7.0)
Requires-Dist: tempdir (==0.7.1)
Provides-Extra: test
Requires-Dist: coverage (>=4.5.3) ; extra == 'test'
Requires-Dist: flake8 (>=3.7.7) ; extra == 'test'
Requires-Dist: pytest (>=4.0.2) ; extra == 'test'
Requires-Dist: python-coveralls (>=2.9.1) ; extra == 'test'
Requires-Dist: twine (>=1.13.0) ; extra == 'test'
Requires-Dist: black ; extra == 'test'
